{
  "collectionName": "components_menu_menus",
  "info": {
    "displayName": "menu",
    "icon": "bulletList",
    "description": ""
  },
  "options": {},
  "attributes": {
    "logo_link": {
      "type": "text",
      "required": true
    },
    "logo_text": {
      "type": "string",
      "required": true
    },
    "logo": {
      "type": "media",
      "multiple": true,
      "required": false,
      "allowedTypes": [
        "images"
      ]
    },
    "menu_links": {
      "type": "component",
      "repeatable": true,
      "component": "menu.menu-link",
      "required": true
    }
  }
}
